MANIFEST.in
README.rst
setup.py
docs/HISTORY.txt
docs/INSTALL.txt
docs/LICENSE.GPL
docs/LICENSE.txt
ftw/__init__.py
ftw.sliderblock.egg-info/PKG-INFO
ftw.sliderblock.egg-info/SOURCES.txt
ftw.sliderblock.egg-info/dependency_links.txt
ftw.sliderblock.egg-info/entry_points.txt
ftw.sliderblock.egg-info/namespace_packages.txt
ftw.sliderblock.egg-info/not-zip-safe
ftw.sliderblock.egg-info/requires.txt
ftw.sliderblock.egg-info/top_level.txt
ftw/sliderblock/__init__.py
ftw/sliderblock/configure.zcml
ftw/sliderblock/lawgiver.zcml
ftw/sliderblock/permissions.zcml
ftw/sliderblock/resources.zcml
ftw/sliderblock/testing.py
ftw/sliderblock/browser/__init__.py
ftw/sliderblock/browser/configure.zcml
ftw/sliderblock/browser/dropzone.py
ftw/sliderblock/browser/sliderblock.py
ftw/sliderblock/browser/resources/main.js
ftw/sliderblock/browser/resources/sliderblock-compiled.js
ftw/sliderblock/browser/resources/sliderblock.js
ftw/sliderblock/browser/resources/styles.scss
ftw/sliderblock/browser/templates/sliderblock.pt
ftw/sliderblock/contents/__init__.py
ftw/sliderblock/contents/configure.zcml
ftw/sliderblock/contents/constraints.py
ftw/sliderblock/contents/interfaces.py
ftw/sliderblock/contents/pane.py
ftw/sliderblock/contents/sliderblock.py
ftw/sliderblock/locales/ftw.sliderblock.pot
ftw/sliderblock/locales/plone.pot
ftw/sliderblock/locales/de/LC_MESSAGES/ftw.sliderblock.po
ftw/sliderblock/locales/de/LC_MESSAGES/plone.po
ftw/sliderblock/locales/en/LC_MESSAGES/ftw.sliderblock.po
ftw/sliderblock/locales/en/LC_MESSAGES/plone.po
ftw/sliderblock/profiles/default/jsregistry.xml
ftw/sliderblock/profiles/default/metadata.xml
ftw/sliderblock/profiles/default/propertiestool.xml
ftw/sliderblock/profiles/default/registry.xml
ftw/sliderblock/profiles/default/rolemap.xml
ftw/sliderblock/profiles/default/types.xml
ftw/sliderblock/profiles/default/workflows.xml
ftw/sliderblock/profiles/default/types/Plone_Site.xml
ftw/sliderblock/profiles/default/types/ftw.simplelayout.ContentPage.xml
ftw/sliderblock/profiles/default/types/ftw.slider.Pane.xml
ftw/sliderblock/profiles/default/types/ftw.sliderblock.SliderBlock.xml
ftw/sliderblock/profiles/default_plone5/metadata.xml
ftw/sliderblock/profiles/default_plone5/registry.xml
ftw/sliderblock/profiles/default_plone5/rolemap.xml
ftw/sliderblock/profiles/default_plone5/types.xml
