Metadata-Version: 2.1
Name: ftw.sliderblock
Version: 2.1.1
Summary: An image slider block to be used on a content page powered by ftw.simplelayout
Home-page: https://github.com/4teamwork/ftw.sliderblock
Author: 4teamwork AG
Author-email: mailto:info@4teamwork.ch
Maintainer: Mathias Leimgruber
License: GPL2
Keywords: ftw plone slider block
Platform: UNKNOWN
Classifier: Framework :: Plone
Classifier: Framework :: Plone :: 4.3
Classifier: Framework :: Plone :: 5.1
Classifier: License :: OSI Approved :: GNU General Public License (GPL)
Classifier: Programming Language :: Python
Classifier: Programming Language :: Python :: 2.7
Classifier: Topic :: Software Development :: Libraries :: Python Modules
Provides-Extra: tests
Provides-Extra: test
